setup.py
ensure_texlive/__init__.py
ensure_texlive/__main__.py
ensure_texlive/version.py
ensure_texlive.egg-info/PKG-INFO
ensure_texlive.egg-info/SOURCES.txt
ensure_texlive.egg-info/dependency_links.txt
ensure_texlive.egg-info/requires.txt
ensure_texlive.egg-info/top_level.txt