Metadata-Version: 2.1
Name: ensure-texlive
Version: 0.0.2
Summary: A small TeXLive distibution installer
Home-page: https://gitlab.com/peczony/ensure_texlive
Author: Alexander Pecheny
Author-email: ap@pecheny.me
Classifier: Programming Language :: Python :: 3
Classifier: License :: OSI Approved :: MIT License
Classifier: Operating System :: OS Independent
